counterweight/__init__.py
counterweight/__main__.py
counterweight/_context_vars.py
counterweight/_utils.py
counterweight/app.py
counterweight/border_healing.py
counterweight/cli.py
counterweight/components.py
counterweight/constants.py
counterweight/controls.py
counterweight/elements.py
counterweight/events.py
counterweight/geometry.py
counterweight/hooks/__init__.py
counterweight/hooks/hooks.py
counterweight/hooks/impls.py
counterweight/hooks/types.py
counterweight/input.py
counterweight/keys.py
counterweight/layout.py
counterweight/logging.py
counterweight/output.py
counterweight/paint.py
counterweight/py.typed
counterweight/shadow.py
counterweight/styles/__init__.py
counterweight/styles/styles.py
counterweight/styles/utilities.py
counterweight/types.py
counterweight-0.0.9.dist-info/LICENSE
counterweight-0.0.9.dist-info/METADATA
counterweight-0.0.9.dist-info/WHEEL
counterweight-0.0.9.dist-info/entry_points.txt
counterweight-0.0.9.dist-info/RECORD
