Metadata-Version: 2.1
Name: counterweight
Version: 0.0.9
Summary: An experimental TUI framework for Python, inspired by React and Tailwind
Home-page: https://github.com/JoshKarpel/counterweight
License: MIT
Keywords: tui,terminal
Author: JoshKarpel
Author-email: josh.karpel@gmail.com
Requires-Python: >=3.11.2,<4
Classifier: Development Status :: 3 - Alpha
Classifier: Environment :: Console
Classifier: Intended Audience :: Developers
Classifier: Intended Audience :: Education
Classifier: License :: OSI Approved :: MIT License
Classifier: Operating System :: MacOS
Classifier: Operating System :: Unix
Classifier: Programming Language :: Python :: 3
Classifier: Programming Language :: Python :: 3.12
Classifier: Programming Language :: Python :: 3 :: Only
Classifier: Programming Language :: Python :: 3.11
Classifier: Topic :: Artistic Software
Classifier: Topic :: Multimedia :: Graphics :: Presentation
Classifier: Typing :: Typed
Requires-Dist: cachetools (>=5.3)
Requires-Dist: more-itertools (>=9.1)
Requires-Dist: parsy (>=2.1)
Requires-Dist: pydantic (>=2)
Requires-Dist: structlog (>=23.1)
Requires-Dist: typer (>=0.9)
Project-URL: Bug Tracker, https://github.com/JoshKarpel/counterweight/issues
Project-URL: Documentation, https://www.counterweight.dev
Project-URL: Repository, https://github.com/JoshKarpel/counterweight
